msx_charset/__init__.py
msx_charset/_version.py
msx_charset/codec_base.py
msx_charset/codec_br.py
msx_charset/codec_intl.py
msx_charset/codec_jp.py
msx_charset-0.1.7.dist-info/licenses/LICENSE
msx_charset-0.1.7.dist-info/METADATA
msx_charset-0.1.7.dist-info/WHEEL
msx_charset-0.1.7.dist-info/top_level.txt
msx_charset-0.1.7.dist-info/RECORD
