Metadata-Version: 2.4
Name: msx-charset
Version: 0.1.7
Summary: MSX character set codecs for Python
Author-email: yamamo-to <humorum@gmail.com>
Project-URL: Repository, https://github.com/yamamo-to/msx-charset
Project-URL: Issue, https://github.com/yamamo-to/msx-charset/issues
Classifier: Development Status :: 4 - Beta
Classifier: Intended Audience :: Developers
Classifier: Programming Language :: Python :: 3
Classifier: Programming Language :: Python :: 3.9
Classifier: Programming Language :: Python :: 3.10
Classifier: Programming Language :: Python :: 3.11
Classifier: Programming Language :: Python :: 3.12
Classifier: Topic :: Software Development :: Libraries :: Python Modules
Requires-Python: >=3.9
License-File: LICENSE
Dynamic: license-file
